politico_civic_race_ratings-0.2.8.dist-info/METADATA
politico_civic_race_ratings-0.2.8.dist-info/RECORD
politico_civic_race_ratings-0.2.8.dist-info/WHEEL
politico_civic_race_ratings-0.2.8.dist-info/top_level.txt
raceratings/__init__.py
raceratings/apps.py
raceratings/celery.py
raceratings/conf.py
raceratings/exceptions.py
raceratings/fields.py
raceratings/signals.py
raceratings/urls.py
raceratings/widgets.py
raceratings/admin/__init__.py
raceratings/admin/page_content.py
raceratings/admin/race.py
raceratings/admin/race_badge.py
raceratings/admin/race_rating.py
raceratings/bin/.DS_Store
raceratings/bin/candidates.xlsx
raceratings/bin/ratings.xlsx
raceratings/bin/csv/governor-candidates.csv
raceratings/bin/csv/governor.csv
raceratings/bin/csv/house-candidates.csv
raceratings/bin/csv/house.csv
raceratings/bin/csv/senate-candidates.csv
raceratings/bin/csv/senate.csv
raceratings/bin/historical-results/csv/daily_kos/2008-2016-president-by-district.csv
raceratings/bin/historical-results/csv/mit_election_lab/1976-2016-house.csv
raceratings/bin/historical-results/csv/mit_election_lab/1976-2016-president.csv
raceratings/bin/historical-results/csv/mit_election_lab/1976-2016-senate.csv
raceratings/bin/historical-results/csv/mit_election_lab/party-standardizer.csv
"raceratings/bin/historical-results/xlsx/Daily Kos/Daily Kos Elections 2008, 2012 & 2016 presidential election results for congressional districts used in 2018 elections.xlsx"
raceratings/management/__init__.py
raceratings/management/commands/__init__.py
raceratings/management/commands/bake_historical_results.py
raceratings/management/commands/bake_pages.py
raceratings/management/commands/bootstrap_content.py
raceratings/management/commands/bootstrap_historical_results_kos.py
raceratings/management/commands/bootstrap_historical_results_mit.py
raceratings/management/commands/bootstrap_ratings.py
raceratings/management/commands/get_candidates.py
raceratings/management/commands/methods/__init__.py
raceratings/managers/__init__.py
raceratings/managers/page_content.py
raceratings/managers/signals.py
raceratings/migrations/0001_initial.py
raceratings/migrations/0002_auto_20180730_2017.py
